{
	"id": "af3b33ab-c987-4da4-96e8-e7e1a0e783c1",
	"name": "Employee CORE",
	"values": [
		{
			"key": "base_url",
			"value": "",
			"type": "default",
			"enabled": true
		},
		{
			"key": "base_auth_url",
			"value": "",
			"type": "default",
			"enabled": true
		},
		{
			"key": "token_admin",
			"value": "",
			"type": "default",
			"enabled": true
		},
		{
			"key": "token_user",
			"value": "",
			"type": "default",
			"enabled": true
		},
		{
			"key": "token_сollaborator",
			"value": "",
			"type": "default",
			"enabled": true
		},
		{
			"key": "refresh_token_collaborator",
			"value": "",
			"type": "default",
			"enabled": true
		},
		{
			"key": "old_token_collaborator",
			"value": "",
			"type": "default",
			"enabled": true
		},
		{
			"key": "no_valid_token_collaborator",
			"value": "",
			"type": "default",
			"enabled": true
		},
		{
			"key": "token_rn",
			"value": "",
			"type": "default",
			"enabled": true
		},
		{
			"key": "refresh_token_rn",
			"value": "",
			"type": "default",
			"enabled": true
		},
		{
			"key": "old_token_rn",
			"value": "",
			"type": "default",
			"enabled": true
		},
		{
			"key": "no_valid_token_rn",
			"value": "",
			"type": "default",
			"enabled": true
		},
		{
			"key": "username_сollaborator",
			"value": "",
			"type": "default",
			"enabled": true
		},
		{
			"key": "password_collaborator",
			"value": "",
			"type": "default",
			"enabled": true
		},
		{
			"key": "employee_id",
			"value": "",
			"type": "default",
			"enabled": true
		},
		{
			"key": "username_rn",
			"value": "",
			"type": "default",
			"enabled": true
		},
		{
			"key": "password_rn",
			"value": "",
			"type": "default",
			"enabled": true
		},
		{
			"key": "default_salary",
			"value": "",
			"type": "default",
			"enabled": true
		},
		{
			"key": "default_startDate",
			"value": "",
			"type": "default",
			"enabled": true
		},
		{
			"key": "default_is_planned",
			"value": "",
			"type": "default",
			"enabled": true
		},
		{
			"key": "default_comment",
			"value": "",
			"type": "default",
			"enabled": true
		},
		{
			"key": "token_account",
			"value": "",
			"type": "any",
			"enabled": true
		},
		{
			"key": "token_top",
			"value": "",
			"type": "any",
			"enabled": true
		},
		{
			"key": "token_sales",
			"value": "",
			"type": "any",
			"enabled": true
		},
		{
			"key": "token_buhgalter",
			"value": "",
			"type": "any",
			"enabled": true
		},
		{
			"key": "token_kadry",
			"value": "",
			"type": "any",
			"enabled": true
		}
	],
	"_postman_variable_scope": "environment",
	"_postman_exported_at": "2023-07-04T13:14:31.207Z",
	"_postman_exported_using": "Postman/10.15.3"
}